typedict/__init__.py
typedict/py.typed
typedict/typedict.py
typedict-0.1.0.dist-info/licenses/LICENSE
typedict-0.1.0.dist-info/METADATA
typedict-0.1.0.dist-info/WHEEL
typedict-0.1.0.dist-info/top_level.txt
typedict-0.1.0.dist-info/RECORD
