Metadata-Version: 2.4
Name: typedict
Version: 0.1.0
Summary: A dict that only uses types as keys. Converts keys used to their type.
Author-email: Odos Matthews <odos@example.com>
Maintainer-email: Odos Matthews <odos@example.com>
License: MIT
Project-URL: Homepage, https://github.com/eddiethedean/typedict
Project-URL: Repository, https://github.com/eddiethedean/typedict
Project-URL: Issues, https://github.com/eddiethedean/typedict/issues
Project-URL: Changelog, https://github.com/eddiethedean/typedict/blob/main/CHANGELOG.md
Keywords: dict,types,type-keys,collections
Classifier: Development Status :: 5 - Production/Stable
Classifier: Intended Audience :: Developers
Classifier: License :: OSI Approved :: MIT License
Classifier: Operating System :: OS Independent
Classifier: Programming Language :: Python :: 3
Classifier: Programming Language :: Python :: 3 :: Only
Classifier: Programming Language :: Python :: 3.11
Classifier: Programming Language :: Python :: 3.12
Classifier: Programming Language :: Python :: 3.13
Classifier: Topic :: Software Development :: Libraries :: Python Modules
Classifier: Topic :: Software Development :: Object Brokering
Classifier: Typing :: Typed
Requires-Python: >=3.11
License-File: LICENSE
Provides-Extra: dev
Requires-Dist: pytest>=7.0.0; extra == "dev"
Requires-Dist: pytest-cov>=4.0.0; extra == "dev"
Requires-Dist: mypy>=1.0.0; extra == "dev"
Requires-Dist: ruff>=0.1.0; extra == "dev"
Requires-Dist: pre-commit>=3.0.0; extra == "dev"
Requires-Dist: tox>=4.0.0; extra == "dev"
Dynamic: license-file
